zhijiang/__init__.py
zhijiang/zhijiang.7z
zhijiang-0.9.54.dist-info/licenses/LICENSE.txt
zhijiang-0.9.54.dist-info/METADATA
zhijiang-0.9.54.dist-info/WHEEL
zhijiang-0.9.54.dist-info/entry_points.txt
zhijiang-0.9.54.dist-info/top_level.txt
zhijiang-0.9.54.dist-info/RECORD
